Metadata-Version: 2.1
Name: PyDocParser
Version: 2.0
Summary: A python client for the DocParser API
Home-page: https://github.com/stautonico/pydocparser
Author: Steve Tautonico
Author-email: stautonico@gmail.com
License: MIT
Keywords: docparser,API,wrapper
Platform: UNKNOWN
Classifier: Development Status :: 5 - Production/Stable
Classifier: Intended Audience :: Developers
Classifier: Topic :: Software Development
Classifier: License :: OSI Approved :: MIT License
Classifier: Programming Language :: Python :: 3
Classifier: Programming Language :: Python :: 3.4
Classifier: Programming Language :: Python :: 3.5
Classifier: Programming Language :: Python :: 3.6
Classifier: Programming Language :: Python :: 3.7
Classifier: Programming Language :: Python :: 3.8
Classifier: Programming Language :: Python :: 3.9
License-File: LICENSE.md
